genai_telemetry/__init__.py
genai_telemetry-1.0.3.dist-info/licenses/LICENSE
genai_telemetry-1.0.3.dist-info/METADATA
genai_telemetry-1.0.3.dist-info/WHEEL
genai_telemetry-1.0.3.dist-info/top_level.txt
genai_telemetry-1.0.3.dist-info/RECORD
