Metadata-Version: 2.4
Name: genai-telemetry
Version: 1.0.3
Summary: Observability SDK for GenAI/LLM applications - supports Splunk, Elasticsearch, OpenTelemetry, Datadog, Prometheus, and more
Author-email: Kamal Singh Bisht <kml.uvce@gmail.com>
License-Expression: Apache-2.0
Project-URL: Homepage, https://github.com/rootiq-ai/genai-telemetry
Project-URL: Repository, https://github.com/rootiq-ai/genai-telemetry
Keywords: genai,llm,observability,telemetry,splunk,elasticsearch,opentelemetry,datadog
Classifier: Development Status :: 5 - Production/Stable
Classifier: Intended Audience :: Developers
Classifier: Programming Language :: Python :: 3
Classifier: Programming Language :: Python :: 3.8
Classifier: Programming Language :: Python :: 3.9
Classifier: Programming Language :: Python :: 3.10
Classifier: Programming Language :: Python :: 3.11
Classifier: Programming Language :: Python :: 3.12
Requires-Python: >=3.8
License-File: LICENSE
Dynamic: license-file
